aplicacion_ejemplo/__init__.py
aplicacion_ejemplo/ejemplo.py
aplicacion_ejemplo_kc_cicd_martinvedani-0.0.3.dist-info/METADATA
aplicacion_ejemplo_kc_cicd_martinvedani-0.0.3.dist-info/WHEEL
aplicacion_ejemplo_kc_cicd_martinvedani-0.0.3.dist-info/top_level.txt
aplicacion_ejemplo_kc_cicd_martinvedani-0.0.3.dist-info/RECORD
