Metadata-Version: 2.1
Name: aplicacion-ejemplo-kc-cicd-martinvedani
Version: 0.0.3
Summary: A small example package
Author: KC
Author-email: martin.vedani@gmail.com
License: UNKNOWN
Platform: UNKNOWN
Requires-Python: >=3.9
Requires-Dist: build
Requires-Dist: twine
Requires-Dist: coloredlogs
